hydro_api/__init__.py
hydro_api/ana/__init__.py
hydro_api/ana/api_biuld.py
hydro_api/ana/tests.py
hydro_api/ana/hidro/__init__.py
hydro_api/ana/hidro/basin.py
hydro_api/ana/hidro/entities.py
hydro_api/ana/hidro/serie_temporal.py
hydro_api/ana/hidro/stations.py
hydro_api/ana/sar/__init__.py
hydro_api/ana/sar/reservoir.py
hydro_api/ana/sar/serie_temporal.py
hydro_python_api-1.1.17.dist-info/LICENSE
hydro_python_api-1.1.17.dist-info/METADATA
hydro_python_api-1.1.17.dist-info/WHEEL
hydro_python_api-1.1.17.dist-info/top_level.txt
hydro_python_api-1.1.17.dist-info/RECORD
