Metadata-Version: 2.1
Name: hydro-python-api
Version: 1.1.17
Summary: Developed for hydrological studies
Home-page: https://github.com/clebsonpy/AnaHidroPythonApi
Author: Clebson Farias
Author-email: clebson2007.farias@gmail.com
License: MIT License
Keywords: ana sar brazil python api
Platform: UNKNOWN
Classifier: Development Status :: 1 - Planning
Classifier: Environment :: Console
Classifier: Intended Audience :: Science/Research
Classifier: Intended Audience :: Developers
Classifier: Intended Audience :: Education
Classifier: License :: OSI Approved :: MIT License
Classifier: Operating System :: OS Independent
Classifier: Programming Language :: Python
Classifier: Topic :: Scientific/Engineering
Classifier: Topic :: Education
License-File: LICENSE
Requires-Dist: defusedxml (==0.7.1)
Requires-Dist: pandas (==1.2.4)
Requires-Dist: requests (==2.25.1)
Requires-Dist: xlrd (==2.0.1)
